{"11":{"max_depth":5,"time_ms":195,"variant":"r","training":0.7,"dataset":"irist","target":"variety"},"12":{"max_depth":5,"time_ms":192,"variant":"r","training":0.7,"dataset":"irist","target":"variety"},"13":{"max_depth":5,"time_ms":729,"variant":"python","training":0.7,"dataset":"irist","target":"variety"},"14":{"max_depth":5,"time_ms":681,"variant":"python","training":0.7,"dataset":"irist","target":"variety"},"15":{"max_depth":5,"time_ms":201,"variant":"r","training":0.7,"dataset":"irist","target":"variety"},"16":{"max_depth":5,"time_ms":202,"variant":"r","training":0.7,"dataset":"irist","target":"variety"},"17":{"max_depth":5,"time_ms":10755,"variant":"julia","training":0.7,"dataset":"irist","target":"variety"},"18":{"max_depth":5,"time_ms":660,"variant":"python","training":0.7,"dataset":"irist","target":"variety"},"19":{"max_depth":5,"time_ms":661,"variant":"python","training":0.7,"dataset":"irist","target":"variety"},"1":{"max_depth":5,"time_ms":731,"variant":"python","training":0.7,"dataset":"irist","target":"variety"},"2":{"max_depth":5,"time_ms":673,"variant":"python","training":0.7,"dataset":"irist","target":"variety"},"3":{"max_depth":5,"time_ms":209,"variant":"r","training":0.7,"dataset":"irist","target":"variety"},"4":{"max_depth":5,"time_ms":203,"variant":"r","training":0.7,"dataset":"irist","target":"variety"},"5":{"max_depth":5,"time_ms":679,"variant":"python","training":0.7,"dataset":"irist","target":"variety"},"6":{"max_depth":5,"time_ms":680,"variant":"python","training":0.7,"dataset":"irist","target":"variety"},"7":{"max_depth":5,"time_ms":196,"variant":"r","training":0.7,"dataset":"irist","target":"variety"},"8":{"max_depth":5,"time_ms":196,"variant":"r","training":0.7,"dataset":"irist","target":"variety"},"9":{"max_depth":5,"time_ms":685,"variant":"python","training":0.7,"dataset":"irist","target":"variety"},"20":{"max_depth":5,"time_ms":206,"variant":"r","training":0.7,"dataset":"irist","target":"variety"},"10":{"max_depth":5,"time_ms":640,"variant":"python","training":0.7,"dataset":"irist","target":"variety"},"21":{"max_depth":5,"time_ms":216,"variant":"r","training":0.7,"dataset":"irist","target":"variety"}}